ralphy/__init__.py
ralphy/__main__.py
ralphy/cli.py
ralphy/config.py
ralphy/git.py
ralphy/progress.py
ralphy/runner.py
ralphy/utils.py
ralphy/engines/__init__.py
ralphy/engines/base.py
ralphy/engines/claude.py
ralphy/engines/codex.py
ralphy/engines/cursor.py
ralphy/engines/droid.py
ralphy/engines/opencode.py
ralphy/engines/qwen.py
ralphy/tasks/__init__.py
ralphy/tasks/base.py
ralphy/tasks/github.py
ralphy/tasks/markdown.py
ralphy/tasks/yaml.py
ralphy-4.0.1.dist-info/licenses/LICENSE
ralphy-4.0.1.dist-info/METADATA
ralphy-4.0.1.dist-info/WHEEL
ralphy-4.0.1.dist-info/entry_points.txt
ralphy-4.0.1.dist-info/top_level.txt
ralphy-4.0.1.dist-info/RECORD
