Metadata-Version: 2.4
Name: ralphy
Version: 4.0.1
Summary: Autonomous AI Coding Loop
Author: Michael Shimeles, Han Wang
License-Expression: MIT
Project-URL: Homepage, https://github.com/hanw/ralphy
Project-URL: Repository, https://github.com/hanw/ralphy
Keywords: ai,coding,automation,claude
Classifier: Development Status :: 4 - Beta
Classifier: Intended Audience :: Developers
Classifier: Programming Language :: Python :: 3
Classifier: Programming Language :: Python :: 3.10
Classifier: Programming Language :: Python :: 3.11
Classifier: Programming Language :: Python :: 3.12
Requires-Python: >=3.10
License-File: LICENSE
Requires-Dist: pyyaml>=6.0
Provides-Extra: dev
Requires-Dist: pytest>=7.0; extra == "dev"
Requires-Dist: pytest-cov>=4.0; extra == "dev"
Requires-Dist: ruff>=0.1.0; extra == "dev"
Dynamic: license-file
